message_builder_bsf/__init__.py
message_builder_bsf/mc_config.py
message_builder_bsf/omeka_project.py
message_builder_bsf/process.py
message_builder_bsf/recipe.py
message_builder_bsf-0.0.2.dist-info/LICENCE
message_builder_bsf-0.0.2.dist-info/METADATA
message_builder_bsf-0.0.2.dist-info/WHEEL
message_builder_bsf-0.0.2.dist-info/top_level.txt
message_builder_bsf-0.0.2.dist-info/RECORD
