Metadata-Version: 2.1
Name: message-builder-bsf
Version: 0.0.2
Summary: Library used to build our messages for our Microservices platform
Home-page: https://github.com/bibliosansfrontieres/message_builder
Author: Steven Wallimann
Author-email: steven.wallimann@bibliosansfrontieres.org
License: UNKNOWN
Platform: UNKNOWN
Classifier: Programming Language :: Python :: 3
Classifier: License :: OSI Approved :: MIT License
Classifier: Operating System :: OS Independent
